README.rst
setup.py
smartanthill/__init__.py
smartanthill/__main__.py
smartanthill/config_base.json
smartanthill/configprocessor.py
smartanthill/exception.py
smartanthill/log.py
smartanthill/service.py
smartanthill/util.py
smartanthill/webrouter.py
smartanthill.egg-info/PKG-INFO
smartanthill.egg-info/SOURCES.txt
smartanthill.egg-info/dependency_links.txt
smartanthill.egg-info/entry_points.txt
smartanthill.egg-info/requires.txt
smartanthill.egg-info/top_level.txt
smartanthill/api/__init__.py
smartanthill/api/handler.py
smartanthill/api/rest.py
smartanthill/api/service.py
smartanthill/cc/__init__.py
smartanthill/cc/compiler.py
smartanthill/cc/service.py
smartanthill/dashboard/__init__.py
smartanthill/dashboard/api.py
smartanthill/dashboard/service.py
smartanthill/device/__init__.py
smartanthill/device/api.py
smartanthill/device/arg.py
smartanthill/device/device.py
smartanthill/device/service.py
smartanthill/device/board/__init__.py
smartanthill/device/board/arduino.py
smartanthill/device/board/base.py
smartanthill/device/board/ti.py
smartanthill/device/operation/__init__.py
smartanthill/device/operation/base.py
smartanthill/device/operation/configure_analog_reference.py
smartanthill/device/operation/configure_pin_mode.py
smartanthill/device/operation/list_operations.py
smartanthill/device/operation/ping.py
smartanthill/device/operation/read_analog_pin.py
smartanthill/device/operation/read_digital_pin.py
smartanthill/device/operation/write_analog_pin.py
smartanthill/device/operation/write_digital_pin.py
smartanthill/litemq/__init__.py
smartanthill/litemq/exchange.py
smartanthill/litemq/service.py
smartanthill/network/__init__.py
smartanthill/network/cdc.py
smartanthill/network/protocol.py
smartanthill/network/service.py
smartanthill/network/zvd.py
smartanthill/test/__init__.py
smartanthill/test/test__configprocessor.py
smartanthill/test/test_litemq.py
smartanthill/test/test_log.py
smartanthill/test/test_network.py
twisted/plugins/smartanthill_cc.py
twisted/plugins/smartanthill_main.py